{
  "hotelUrl": "https://www.google.com/travel/hotels/casablanca/entity/CgsIhK66qOrqjImTARAB?hl=fr&utm_campaign=sharing&utm_medium=link&utm_source=htls&ts=CAESABouChASDDoKQ2FzYWJsYW5jYRoAEhoSFAoHCOUPEAwYCRIHCOUPEAwYChgBMgIQACoLCgcoAToDTUFEGgA&ved=2ahUKEwjmh5Cmmqf0AhXuHwYAHe52Bl8QyvcEegUIARCrAQ&rp=OAE",
  "hotelName": "Hôtel Central",
  "mainPrice": "299 MAD",
  "adress": "20, Place Ahmad El Bidaoui، Casablanca 23000",
  "phone": "05222-62525",
  "rating": "3,6",
  "hotelStar": "Hôtel 2 étoiles",
  "reviewsNumber": "456 avis",
  "website": "http://www.hotelcentralcasa.com/",
  "description": "NULL",
  "popularAmenties": "",
  "internet": "Wi-Fi\ngratuit",
  "policiesAndPayments": "Établissement non-fumeur",
  "enfants": "Adapté aux enfants",
  "Bars_Restaurants": "Restaurant | Petit-déjeuner\ngratuit",
  "piscines": "Pas de piscine"
}